bps_fbi_sp_ecoli/__init__.py
bps_fbi_sp_ecoli/_modidx.py
bps_fbi_sp_ecoli/core.py
bps_fbi_sp_ecoli/hello_world.py
bps_fbi_sp_ecoli/helpers.py
bps_fbi_sp_ecoli/qc_ecoli_pipeline.py
bps_fbi_sp_ecoli/run_ecolityping.py
bps_fbi_sp_ecoli/run_postecolityping.py
bps_fbi_sp_ecoli/run_qcecolisummary.py
bps_fbi_sp_ecoli/config/config.default.env
bps_fbi_sp_ecoli/config/config.default.yaml
bps_fbi_sp_ecoli/ecoli_fbi/__init__.py
bps_fbi_sp_ecoli/ecoli_fbi/ecolityping.py
bps_fbi_sp_ecoli/ecoli_fbi/postecolityping.py
bps_fbi_sp_ecoli/ecoli_fbi/qcecolisummary.py
bps_fbi_sp_ecoli/scripts/__init__.py
bps_fbi_sp_ecoli/scripts/ecolityping.py
bps_fbi_sp_ecoli/scripts/postecolityping.py
bps_fbi_sp_ecoli/scripts/qc_ecoli_summary.py
bps_fbi_sp_ecoli-0.0.7.dist-info/LICENSE
bps_fbi_sp_ecoli-0.0.7.dist-info/METADATA
bps_fbi_sp_ecoli-0.0.7.dist-info/WHEEL
bps_fbi_sp_ecoli-0.0.7.dist-info/entry_points.txt
bps_fbi_sp_ecoli-0.0.7.dist-info/top_level.txt
bps_fbi_sp_ecoli-0.0.7.dist-info/RECORD
